{"cameraMode":{"drawMode":0,"name":"Shaded","section":"Shading Mode"},"sceneLighting":false,"audioPlay":false,"sceneViewState":{"showFog":true,"showMaterialUpdate":false,"showSkybox":false,"showFlares":true,"showImageEffects":true,"showParticleSystems":true},"in2DMode":false,"pivot":{"x":-0.009657908231019974,"y":1.0564874410629273,"z":2.4346821308135988},"rotation":{"x":0.007433408871293068,"y":0.9891157150268555,"z":-0.13676497340202332,"w":0.05376137048006058},"size":0.027707815170288087,"orthographic":false}